LICENSE
README.md
pyproject.toml
setup.cfg
setup.py
virtualisation_resource_distributor/CLI.py
virtualisation_resource_distributor/__init__.py
virtualisation_resource_distributor/config.py
virtualisation_resource_distributor/database.py
virtualisation_resource_distributor/models.py
virtualisation_resource_distributor/proxmox.py
virtualisation_resource_distributor/schemas.py
virtualisation_resource_distributor.egg-info/PKG-INFO
virtualisation_resource_distributor.egg-info/SOURCES.txt
virtualisation_resource_distributor.egg-info/dependency_links.txt
virtualisation_resource_distributor.egg-info/entry_points.txt
virtualisation_resource_distributor.egg-info/requires.txt
virtualisation_resource_distributor.egg-info/top_level.txt
virtualisation_resource_distributor/crud/__init__.py
virtualisation_resource_distributor/crud/base_database.py
virtualisation_resource_distributor/crud/base_proxmox.py
virtualisation_resource_distributor/crud/crud_database_node.py
virtualisation_resource_distributor/crud/crud_database_zone.py
virtualisation_resource_distributor/crud/crud_proxmox_member.py
virtualisation_resource_distributor/crud/crud_proxmox_pool.py