Metadata-Version: 2.1
Name: virtualisation-resource-distributor
Version: 3.1.2
Summary: Program to distribute Virtual Machines and Containers over Proxmox zones
Home-page: https://github.com/CyberfusionNL/Virtualisation-Resource-Distributor
Author: William Edwards
Author-email: opensource@cyberfusion.nl
License: MIT
Keywords: cyberfusion,proxmox,virtualisation
Platform: linux
Classifier: Programming Language :: Python :: 3
Classifier: License :: OSI Approved :: MIT License
Classifier: Operating System :: OS Independent
Requires-Python: >=3.6
License-File: LICENSE
